more_decorators/__init__.py
more_decorators/runtime_defaults.py
more_decorators-0.1.1.dist-info/LICENSE
more_decorators-0.1.1.dist-info/METADATA
more_decorators-0.1.1.dist-info/WHEEL
more_decorators-0.1.1.dist-info/RECORD
