Metadata-Version: 2.1
Name: more-decorators
Version: 0.1.1
Summary: Python decorators library
License: MIT
Author: Leo Sin
Author-email: leo.sin@my.cityu.edu.hk
Requires-Python: >=3.10,<4.0
Classifier: License :: OSI Approved :: MIT License
Classifier: Programming Language :: Python :: 3
Classifier: Programming Language :: Python :: 3.10
Classifier: Programming Language :: Python :: 3.11
Classifier: Programming Language :: Python :: 3.12
Provides-Extra: docs
Requires-Dist: myst-parser (>=2.0.0,<3.0.0) ; extra == "docs"
Requires-Dist: sphinx (>=7.2.6,<8.0.0) ; extra == "docs"
Requires-Dist: sphinx-autoapi (>=3.0.0,<4.0.0) ; extra == "docs"
Requires-Dist: sphinx-pyproject (>=0.3.0,<0.4.0) ; extra == "docs"
Requires-Dist: sphinx-rtd-theme (>=2.0.0,<3.0.0) ; extra == "docs"
Requires-Dist: sphinxcontrib-apidoc (>=0.5.0,<0.6.0) ; extra == "docs"
